odoo/addons/calendar_export_ics/README.rst
odoo/addons/calendar_export_ics/__init__.py
odoo/addons/calendar_export_ics/__manifest__.py
odoo/addons/calendar_export_ics/i18n/calendar_export_ics.pot
odoo/addons/calendar_export_ics/i18n/it.po
odoo/addons/calendar_export_ics/readme/CONTRIBUTORS.md
odoo/addons/calendar_export_ics/readme/DESCRIPTION.md
odoo/addons/calendar_export_ics/readme/USAGE.md
odoo/addons/calendar_export_ics/security/calendar_export_security.xml
odoo/addons/calendar_export_ics/security/ir.model.access.csv
odoo/addons/calendar_export_ics/static/description/icon.png
odoo/addons/calendar_export_ics/static/description/index.html
odoo/addons/calendar_export_ics/tests/__init__.py
odoo/addons/calendar_export_ics/tests/test_calendar_export_ics.py
odoo/addons/calendar_export_ics/wizards/__init__.py
odoo/addons/calendar_export_ics/wizards/wizard_export_ics.py
odoo/addons/calendar_export_ics/wizards/wizard_export_ics.xml
odoo_addon_calendar_export_ics-18.0.1.0.1.4.dist-info/METADATA
odoo_addon_calendar_export_ics-18.0.1.0.1.4.dist-info/WHEEL
odoo_addon_calendar_export_ics-18.0.1.0.1.4.dist-info/top_level.txt
odoo_addon_calendar_export_ics-18.0.1.0.1.4.dist-info/RECORD
