Metadata-Version: 2.1
Name: odoo-addon-calendar_export_ics
Version: 18.0.1.0.1.4
Requires-Python: >=3.10
Requires-Dist: odoo==18.0.*
Summary: Allow exporting odoo calendar to an ics file
Home-page: https://github.com/OCA/calendar
License: AGPL-3
Author: ForgeFlow S.L.,Odoo Community Association (OCA)
Author-email: support@odoo-community.org
Classifier: Programming Language :: Python
Classifier: Framework :: Odoo
Classifier: Framework :: Odoo :: 18.0
Classifier: License :: OSI Approved :: GNU Affero General Public License v3
